vidspy/__init__.py
vidspy/cli.py
vidspy/core.py
vidspy/metrics.py
vidspy/modules.py
vidspy/optimizers.py
vidspy/providers.py
vidspy/py.typed
vidspy/setup.py
vidspy/signatures.py
vidspy-0.1.3.dist-info/licenses/LICENSE
vidspy-0.1.3.dist-info/METADATA
vidspy-0.1.3.dist-info/WHEEL
vidspy-0.1.3.dist-info/entry_points.txt
vidspy-0.1.3.dist-info/top_level.txt
vidspy-0.1.3.dist-info/RECORD
