Metadata-Version: 2.4
Name: vidspy
Version: 0.1.3
Summary: DSPy-style framework for optimizing text-to-video generation via VBench metric feedback
Author-email: Leo Chow <leo_ckl@hotmail.com>
Maintainer-email: Leo Chow <leo_ckl@hotmail.com>
License: MIT
Project-URL: Homepage, https://github.com/leockl/vidspy
Project-URL: Documentation, https://github.com/leockl/vidspy#readme
Project-URL: Repository, https://github.com/leockl/vidspy
Project-URL: Issues, https://github.com/leockl/vidspy/issues
Keywords: video-generation,text-to-video,dspy,vbench,prompt-optimization,few-shot-learning,machine-learning,deep-learning
Classifier: Development Status :: 3 - Alpha
Classifier: Intended Audience :: Developers
Classifier: Intended Audience :: Science/Research
Classifier: License :: OSI Approved :: MIT License
Classifier: Operating System :: OS Independent
Classifier: Programming Language :: Python :: 3
Classifier: Programming Language :: Python :: 3.9
Classifier: Programming Language :: Python :: 3.10
Classifier: Programming Language :: Python :: 3.11
Classifier: Programming Language :: Python :: 3.12
Classifier: Topic :: Scientific/Engineering :: Artificial Intelligence
Classifier: Topic :: Multimedia :: Video
Requires-Python: >=3.9
License-File: LICENSE
Requires-Dist: dspy-ai>=2.4.0
Requires-Dist: torch>=2.0.0
Requires-Dist: numpy>=1.21.0
Requires-Dist: Pillow>=9.0.0
Requires-Dist: opencv-python>=4.5.0
Requires-Dist: requests>=2.25.0
Requires-Dist: tqdm>=4.60.0
Requires-Dist: pydantic>=2.0.0
Requires-Dist: PyYAML>=6.0.0
Provides-Extra: vbench
Requires-Dist: vbench>=0.1.0; extra == "vbench"
Provides-Extra: dev
Requires-Dist: pytest>=7.0.0; extra == "dev"
Requires-Dist: pytest-cov>=4.0.0; extra == "dev"
Requires-Dist: black>=23.0.0; extra == "dev"
Requires-Dist: isort>=5.12.0; extra == "dev"
Requires-Dist: mypy>=1.0.0; extra == "dev"
Requires-Dist: ruff>=0.1.0; extra == "dev"
Provides-Extra: all
Requires-Dist: vidspy[dev,vbench]; extra == "all"
Dynamic: license-file
